openrecon/__init__.py
openrecon/__version__.py
openrecon/cli.py
openrecon/core/CMSfingerprints.py
openrecon/core/SQLdetector.py
openrecon/core/__init__.py
openrecon/core/auth_handler.py
openrecon/core/check_compat.py
openrecon/core/colors.py
openrecon/core/context.py
openrecon/core/crawler.py
openrecon/core/httpClient.py
openrecon/core/macLookUp.py
openrecon/core/models.py
openrecon/core/parsers.py
openrecon/core/payloadModels.py
openrecon/core/payload_handler.py
openrecon/core/progress.py
openrecon/core/reporter.py
openrecon/core/util.py
openrecon/scanners/__init__.py
openrecon/scanners/netDisc.py
openrecon/scanners/pingSweep.py
openrecon/scanners/portScanner.py
openrecon/scanners/subDomainEnum.py
openrecon/scanners/utils/__init__.py
openrecon/scanners/utils/user_agents.py
openrecon/webVulns/CMSdetector.py
openrecon/webVulns/SQLiS.py
openrecon/webVulns/XSSscanner.py
openrecon/webVulns/__init__.py
openrecon/webVulns/csrf.py
openrecon/webVulns/graphQL.py
openrecon-0.1.7.dist-info/licenses/LICENSE
openrecon-0.1.7.dist-info/METADATA
openrecon-0.1.7.dist-info/WHEEL
openrecon-0.1.7.dist-info/entry_points.txt
openrecon-0.1.7.dist-info/top_level.txt
openrecon-0.1.7.dist-info/RECORD
