Metadata-Version: 2.4
Name: openrecon
Version: 0.1.7
Summary: A lightweight, modular cybersecurity scanner
Home-page: https://github.com/R0salman/OpenRecon
Author: R0salman
Author-email: salmanalmtyry522@gmail.com
Project-URL: Bug Reports, https://github.com/R0salman/OpenRecon/issues
Project-URL: Source, https://github.com/R0salman/OpenRecon
Project-URL: Documentation, https://r0salman.github.io/OpenRecon/
Keywords: security,vulnerability scanner,xss,sql injection,cms detection,web security,penetration testing,reconnaissance,subdomain enumeration,port scanning
Platform: any
Classifier: Development Status :: 3 - Alpha
Classifier: Intended Audience :: Information Technology
Classifier: Intended Audience :: System Administrators
Classifier: Topic :: Security
Classifier: Topic :: System :: Networking :: Monitoring
Classifier: Topic :: System :: Systems Administration
Classifier: License :: OSI Approved :: MIT License
Classifier: Programming Language :: Python :: 3
Classifier: Programming Language :: Python :: 3.8
Classifier: Programming Language :: Python :: 3.9
Classifier: Programming Language :: Python :: 3.10
Classifier: Programming Language :: Python :: 3.11
Classifier: Programming Language :: Python :: 3.12
Classifier: Operating System :: OS Independent
Classifier: Environment :: Console
Requires-Python: >=3.8
License-File: LICENSE
Requires-Dist: rich>=13.0.0
Requires-Dist: python-nmap>=0.7.1
Requires-Dist: requests>=2.31.0
Requires-Dist: aiohttp>=3.8.0
Requires-Dist: beautifulsoup4>=4.12.0
Requires-Dist: dnspython>=2.3.0
Requires-Dist: lxml>=4.9.0
Requires-Dist: urllib3>=2.0.0
Requires-Dist: validators>=0.20.0
Requires-Dist: pathlib>=1.0.1
Requires-Dist: scapy>=2.6.1
Requires-Dist: httpx>=0.28.1
Requires-Dist: argparse>=1.4.0
Requires-Dist: asyncio>=3.4.3
Requires-Dist: regex>=2024.11.6
Dynamic: author
Dynamic: author-email
Dynamic: classifier
Dynamic: description
Dynamic: description-content-type
Dynamic: home-page
Dynamic: keywords
Dynamic: license-file
Dynamic: platform
Dynamic: project-url
Dynamic: requires-dist
Dynamic: requires-python
Dynamic: summary
